{
  "preview": [
    {
      "paragraph": [
        {
          "sentence": [
            {
              "char": "原",
              "pinyin": "yuán"
            },
            {
              "char": "来",
              "pinyin": "lái"
            },
            {
              "char": "姹",
              "pinyin": "chà"
            },
            {
              "char": "紫",
              "pinyin": "zǐ"
            },
            {
              "char": "嫣",
              "pinyin": "yān"
            },
            {
              "char": "红",
              "pinyin": "hóng"
            },
            {
              "char": "开",
              "pinyin": "kāi"
            },
            {
              "char": "遍",
              "pinyin": "biàn"
            },
            {
              "char": "，",
              "pinyin": "　"
            },
            {
              "char": "似",
              "pinyin": "sì"
            },
            {
              "char": "这",
              "pinyin": "zhè"
            },
            {
              "char": "般",
              "pinyin": "bān"
            },
            {
              "char": "都",
              "pinyin": "dōu"
            },
            {
              "char": "付",
              "pinyin": "fù"
            },
            {
              "char": "与",
              "pinyin": "yǔ"
            },
            {
              "char": "断",
              "pinyin": "duàn"
            },
            {
              "char": "井",
              "pinyin": "jǐng"
            },
            {
              "char": "颓",
              "pinyin": "tuí"
            },
            {
              "char": "垣",
              "pinyin": "yuán"
            },
            {
              "char": "。",
              "pinyin": "　"
            }
          ],
          "translation": {
            "translation": "这样繁花似锦的春色无人赏识，只能存在于这破败的断壁残垣之中。"
          },
          "notes": [
            {
              "start": 0,
              "end": 2,
              "note": "原来：在此处意为‘本来’，非现代汉语中表示发现或醒悟的副词。"
            },
            {
              "start": 3,
              "end": 6,
              "note": "姹紫嫣红：形容百花娇艳盛开。姹，美丽；嫣，美好。"
            },
            {
              "start": 14,
              "end": 19,
              "note": "断井颓垣：指破败的井台和倒塌的墙垣，形容庭院荒芜。"
            }
          ]
        },
        {
          "sentence": [
            {
              "char": "良",
              "pinyin": "liáng"
            },
            {
              "char": "辰",
              "pinyin": "chén"
            },
            {
              "char": "美",
              "pinyin": "měi"
            },
            {
              "char": "景",
              "pinyin": "jǐng"
            },
            {
              "char": "奈",
              "pinyin": "nài"
            },
            {
              "char": "何",
              "pinyin": "hé"
            },
            {
              "char": "天",
              "pinyin": "tiān"
            },
            {
              "char": "，",
              "pinyin": "　"
            },
            {
              "char": "赏",
              "pinyin": "shǎng"
            },
            {
              "char": "心",
              "pinyin": "xīn"
            },
            {
              "char": "乐",
              "pinyin": "lè"
            },
            {
              "char": "事",
              "pinyin": "shì"
            },
            {
              "char": "谁",
              "pinyin": "shuí"
            },
            {
              "char": "家",
              "pinyin": "jiā"
            },
            {
              "char": "院",
              "pinyin": "yuàn"
            },
            {
              "char": "！",
              "pinyin": "　"
            }
          ],
          "translation": {
            "translation": "这美好的景色、美好的时光让我怎样面对，那让人欢心愉快的事究竟在谁家的院子里上演？"
          },
          "notes": [
            {
              "start": 0,
              "end": 7,
              "note": "良辰美景奈何天：意为美好的时光和景色，却无奈天意弄人。奈何，如何、怎么办。"
            },
            {
              "start": 8,
              "end": 15,
              "note": "赏心乐事谁家院：使人心情愉悦的乐事，不知发生在谁家的庭院。谁家，哪一家。"
            }
          ]
        },
        {
          "sentence": [
            {
              "char": "朝",
              "pinyin": "zhāo"
            },
            {
              "char": "飞",
              "pinyin": "fēi"
            },
            {
              "char": "暮",
              "pinyin": "mù"
            },
            {
              "char": "卷",
              "pinyin": "juǎn"
            },
            {
              "char": "，",
              "pinyin": "　"
            },
            {
              "char": "云",
              "pinyin": "yún"
            },
            {
              "char": "霞",
              "pinyin": "xiá"
            },
            {
              "char": "翠",
              "pinyin": "cuì"
            },
            {
              "char": "轩",
              "pinyin": "xuān"
            },
            {
              "char": "；",
              "pinyin": "　"
            }
          ],
          "translation": {
            "translation": "朝云铺扬，暮云卷收；云霞映着亭台楼阁；"
          },
          "notes": [
            {
              "start": 0,
              "end": 4,
              "note": "朝飞暮卷：形容云霞或画卷在早晚舒展卷起，此处借指时光流转、景色变幻。"
            },
            {
              "start": 5,
              "end": 9,
              "note": "云霞翠轩：云霞映照着的华美亭台。翠轩，装饰华丽的楼阁。"
            }
          ]
        },
        {
          "sentence": [
            {
              "char": "雨",
              "pinyin": "yǔ"
            },
            {
              "char": "丝",
              "pinyin": "sī"
            },
            {
              "char": "风",
              "pinyin": "fēng"
            },
            {
              "char": "片",
              "pinyin": "piàn"
            },
            {
              "char": "，",
              "pinyin": "　"
            },
            {
              "char": "烟",
              "pinyin": "yān"
            },
            {
              "char": "波",
              "pinyin": "bō"
            },
            {
              "char": "画",
              "pinyin": "huà"
            },
            {
              "char": "船",
              "pinyin": "chuán"
            },
            {
              "char": "，",
              "pinyin": "　"
            }
          ],
          "translation": {
            "translation": "细雨几丝，和风片片，烟波浩渺的春水中浮动着画船，"
          },
          "notes": [
            {
              "start": 0,
              "end": 4,
              "note": "雨丝风片：细雨如丝，微风轻拂。片，形容微风轻柔。"
            },
            {
              "start": 5,
              "end": 9,
              "note": "烟波画船：烟雾笼罩的水面上装饰华美的游船。"
            }
          ]
        },
        {
          "sentence": [
            {
              "char": "锦",
              "pinyin": "jǐn"
            },
            {
              "char": "屏",
              "pinyin": "píng"
            },
            {
              "char": "人",
              "pinyin": "rén"
            },
            {
              "char": "忒",
              "pinyin": "tuī"
            },
            {
              "char": "看",
              "pinyin": "kàn"
            },
            {
              "char": "的",
              "pinyin": "de"
            },
            {
              "char": "这",
              "pinyin": "zhè"
            },
            {
              "char": "韶",
              "pinyin": "sháo"
            },
            {
              "char": "光",
              "pinyin": "guāng"
            },
            {
              "char": "贱",
              "pinyin": "jiàn"
            },
            {
              "char": "！",
              "pinyin": "　"
            }
          ],
          "translation": {
            "translation": "我这被阻隔在深闺中的人太辜负这大好春光。"
          },
          "notes": [
            {
              "start": 0,
              "end": 2,
              "note": "锦屏人：指深闺中的女子。锦屏，华丽的屏风，代指闺阁。"
            },
            {
              "start": 3,
              "end": 5,
              "note": "忒看的：太看得。忒，太、过于；看的，看得。"
            },
            {
              "start": 6,
              "end": 10,
              "note": "韶光贱：美好的春光被轻视。韶光，春光；贱，轻视、浪费。"
            }
          ]
        }
      ]
    }
  ],
  "mode": "paragraph"
}